[
    {
        "id": "vent-ring",
        "name": "Vent Ring",
        "description": "Ring/cylinder (48.2mm outer, 46.4mm inner, 5mm height) - Made to help snug a vent cover fitting",
        "file": "./vent-ring.js"
    },
    {
        "id": "hexagon",
        "name": "Custom Hexagon",
        "description": "Hexagon (120mm x 60mm x 1mm with triangular extensions)",
        "file": "./hexagon.js"
    },
    {
        "id": "gridfinity-test",
        "name": "Gridfinity Test Box",
        "description": "Gridfinity box (2x1 units, 0.5 height) - Configurable storage box on gridfinity base",
        "file": "./gridfinity-test.js"
    },
    {
        "id": "gridfinity-screwdriver",
        "name": "Gridfinity Screwdriver Holder",
        "description": "Gridfinity box with customizable bars and cylinder cutouts for holding screwdrivers",
        "file": "./gridfinity-screwdriver.js"
    },
    {
        "id": "gridfinity-screwdriver-dual",
        "name": "Gridfinity Dual Screwdriver Holder",
        "description": "Gridfinity box with 2 bars and alternating cutouts for screwdrivers facing opposite directions",
        "file": "./gridfinity-screwdriver-dual.js"
    },
    {
        "id": "gridfinity-shaver-box",
        "name": "Gridfinity Shaver Box",
        "description": "Gridfinity box (2x3 units, 42mm tall) with side wall cutouts for easy shaver access",
        "file": "./gridfinity-shaver-box.js"
    },
    {
        "id": "christmas-ornament",
        "name": "Christmas Ornament",
        "description": "Flat ornament ball with hanging knob for sticker application",
        "file": "./christmas-ornament.js"
    },
    {
        "id": "dupont-strap",
        "name": "DuPont Strap",
        "description": "Rectangular strap for holding singular DuPont connectors with configurable pin count",
        "file": "./dupont-strap.js"
    }
]

